CHANGES.txt
MANIFEST.in
README.txt
noolite
noolite.py
setup.py
tests.py
noolite.egg-info/PKG-INFO
noolite.egg-info/SOURCES.txt
noolite.egg-info/dependency_links.txt
noolite.egg-info/requires.txt
noolite.egg-info/top_level.txt