Metadata-Version: 1.1
Name: noolite
Version: 1.1.2
Summary: Class for NooLite USB stick
Home-page: https://github.com/Sicness/pyNooLite
Author: Anton Balashov
Author-email: sicness@darklogic.ru
License: GPLv3
Keywords: noolite,USB,smarthome,PC118,PC116,PC1132
Platform: any
Classifier: Programming Language :: Python
Classifier: Programming Language :: Python :: 3
Classifier: Development Status :: 4 - Beta
Classifier: Intended Audience :: Developers
Classifier: Intended Audience :: Manufacturing
Classifier: License :: OSI Approved :: GNU General Public License v3 (GPLv3)
Classifier: Operating System :: POSIX :: Linux
Classifier: Topic :: Software Development :: Libraries :: Python Modules
Classifier: Topic :: Home Automation
Classifier: Topic :: System :: Hardware
